pysdsbapi/__init__.py
pysdsbapi/auth.py
pysdsbapi/bridge.py
pysdsbapi/bridgeAPI.py
pysdsbapi/module.py
pysdsbapi/user.py
pysdsbapi-0.9.3.dist-info/LICENSE
pysdsbapi-0.9.3.dist-info/METADATA
pysdsbapi-0.9.3.dist-info/WHEEL
pysdsbapi-0.9.3.dist-info/top_level.txt
pysdsbapi-0.9.3.dist-info/RECORD
