Metadata-Version: 2.1
Name: pysdsbapi
Version: 0.9.3
Summary: Experimental library for interacting with the experimental sds bridge api.
Home-page: UNKNOWN
Author: mlad_Blum
License: MIT
Platform: UNKNOWN
Classifier: Development Status :: 2 - Pre-Alpha
Classifier: Programming Language :: Python :: 3
Classifier: License :: OSI Approved :: MIT License
Classifier: Operating System :: OS Independent
Requires-Python: >=3.6
License-File: LICENSE
Requires-Dist: aiohttp (<4,>=3.7.0)
